sudoku/__init__.py
sudoku/_modidx.py
sudoku/board.py
sudoku/cell.py
sudoku/main.py
sudoku_board_solver_em-0.0.2.dist-info/licenses/LICENSE
sudoku_board_solver_em-0.0.2.dist-info/METADATA
sudoku_board_solver_em-0.0.2.dist-info/WHEEL
sudoku_board_solver_em-0.0.2.dist-info/entry_points.txt
sudoku_board_solver_em-0.0.2.dist-info/top_level.txt
sudoku_board_solver_em-0.0.2.dist-info/RECORD
